flowprint/__init__.py
flowprint/__main__.py
flowprint/browser_detector.py
flowprint/cluster.py
flowprint/cross_correlation_graph.py
flowprint/fingerprint.py
flowprint/fingerprints.py
flowprint/flow_generator.py
flowprint/flowprint.py
flowprint/flows.py
flowprint/network_destination.py
flowprint/preprocessor.py
flowprint/reader.py
flowprint-1.0.5.dist-info/LICENSE
flowprint-1.0.5.dist-info/METADATA
flowprint-1.0.5.dist-info/WHEEL
flowprint-1.0.5.dist-info/top_level.txt
flowprint-1.0.5.dist-info/RECORD
