Metadata-Version: 2.1
Name: flowprint
Version: 1.0.5
Summary: FlowPrint: Semi-Supervised Mobile-App Fingerprinting on Encrypted Network Traffic
Home-page: https://github.com/Thijsvanede/FlowPrint
Author: Thijs van Ede
Author-email: t.s.vanede@utwente.nl
License: UNKNOWN
Platform: UNKNOWN
Classifier: Programming Language :: Python :: 3
Classifier: License :: OSI Approved :: MIT License
Classifier: Operating System :: OS Independent
